checkin
dist
