Metadata-Version: 2.1
Name: checkin-webapp
Version: 0.0.5
Summary: Simple backend application to learn how to make a web app
Author-email: Evan Voyles <ejovo13@yahoo.com>
Classifier: Programming Language :: Python :: 3
Classifier: License :: OSI Approved :: MIT License
Classifier: Operating System :: OS Independent
Requires-Python: >=3.10
